[
  {
    "name": "bcdec", 
    "number": "7656441"
  }, 
  {
    "name": "eeeca", 
    "number": "5464645"
  }, 
  {
    "name": "decda", 
    "number": "3427232"
  }, 
  {
    "name": "eceed", 
    "number": "2646367"
  }, 
  {
    "name": "ebacd", 
    "number": "3754214"
  }, 
  [
    {
      "name": "bcdec", 
      "number": "7656441"
    }, 
    {
      "name": "eeeca", 
      "number": "5464645"
    }, 
    {
      "name": "decda", 
      "number": "3427232"
    }, 
    {
      "name": "eceed", 
      "number": "2646367"
    }, 
    {
      "name": "ebacd", 
      "number": "3754214"
    }
  ]
]